tcav/__init__.py
tcav/activation_generator.py
tcav/cav.py
tcav/cav_test.py
tcav/model.py
tcav/model_test.py
tcav/run_params.py
tcav/tcav.py
tcav/tcav_test.py
tcav/utils.py
tcav/utils_plot.py
tcav/utils_test.py
tcav/tcav_examples/__init__.py
tcav/tcav_examples/discrete/__init__.py
tcav/tcav_examples/discrete/kdd99_activation_generator.py
tcav/tcav_examples/discrete/kdd99_model.py
tcav/tcav_examples/discrete/kdd99_model_wrapper.py
tcav/tcav_examples/discrete/make_kdd99_concepts.py
tcav/tcav_examples/image_models/__init__.py
tcav/tcav_examples/image_models/imagenet/__init__.py
tcav/tcav_examples/image_models/imagenet/download_and_make_datasets.py
tcav/tcav_examples/image_models/imagenet/imagenet_and_broden_fetcher.py
tcav/tcav_results/__init__.py
tcav/tcav_results/results_pb2.py
tcav-0.2.2.dist-info/LICENSE
tcav-0.2.2.dist-info/METADATA
tcav-0.2.2.dist-info/WHEEL
tcav-0.2.2.dist-info/top_level.txt
tcav-0.2.2.dist-info/RECORD
