Metadata-Version: 2.1
Name: tcav
Version: 0.2.2
Summary: Testing with Concept Activation Vectors code
Home-page: http://github.com/tensorflow/tcav
Author: Google Inc.
Author-email: opensource@google.com
License: Apache 2.0
Platform: UNKNOWN
Requires-Dist: matplotlib (>=2.2.4)
Requires-Dist: Pillow (>=6.0.0)
Requires-Dist: scikit-learn (>=0.20.3)
Requires-Dist: scipy (>=1.2.1)
Requires-Dist: protobuf (>=3.10.0)
